[
    {
        "document_n": "90"
    },
    {
        "id": "0",
        "index": 0,
        "bold": 1,
        "weight": 1,
        "text": "디더블유에스자산운용㈜는 이 투자신탁의 실제 수익률 변동성을감안하여2 등급으로분류하였습니다."
    },
    {
        "id": "0",
        "index": 1,
        "bold": 0,
        "weight": 1,
        "text": "집합투자증권은｢예금자 보호법｣에따라예금보험공사가보호하지않는 실적배당 상품 이며,집합투자기구 재산의50% 이상을 BRI Cs( 브라질,러시아,인도 ,중국) 국가와 관련된 주식에 투자하 는집합 투자증권 에주로투자하며 ,이 에따른집합 투자 증권 등의가격변동 위험 ,신흥국 의상대 적으로높 은불안정성 에따른신흥국가위험,환율변동위험등이있 으므로투자에신중을기하여주시기 바랍니다."
    },
    {
        "id": "1",
        "index": 0,
        "bold": 0,
        "weight": 1,
        "text": "이 집합투자기구는 주로 브릭스 (브라질, 러시아, 인도, 중국) 국가에 투자하는 집합투자증 권에 주로 투자하여 피투자 집합투자증권의 가격 상승시 자본이득을 추구합니다."
    },
    {
        "id": "1",
        "index": 1,
        "bold": 0,
        "weight": 1,
        "text": "이 집합 투자기구는 시장상황에 따라 적극적인 매매전략을 구사하므로 빈번한 매매로 인하여 매매 비용이 증가하여, 집합투자기구 비용의 증가를 야기할 수 있습니다."
    },
    {
        "id": "1",
        "index": 2,
        "bold": 0,
        "weight": 1,
        "text": "비교지수: MSCI BRIC Index 90% + 콜금리 10% (비교지수 변경 시 디더블유에스자산운용, 판매회사 및 금융투자협회 홈페이지 등을 통해 공시 및 통보) ※상기의 투자목적이 반드시 달성된다는 보장은 없으며, 집합투자업자, 신탁업자, 판매회사 등 이 투자신탁과 관 련된 어떤 당사자도 투자원금의 보장 또는 투자목적의 달성을 보장하지 아니합니다."
    },
    {
        "id": "1",
        "index": 3,
        "bold": 0,
        "weight": 1,
        "text": "※자세한 내용은 투자설명서(제2부. 9.집합투자기구의 투자전략, 투자방침 및 수익구조를 참조바랍니다."
    },
    {
        "id": "1",
        "index": 4,
        "bold": 0,
        "weight": 1,
        "text": "투자자가 부담하는 수수료 및 총보수 1,000 만원 투자시 투자자가 부담하는 투자기간별 총비용 예시 (단위: 천원) 수수료미징구- 오프라인형 (C3) 없음"
    },
    {
        "id": "1",
        "index": 5,
        "bold": 0,
        "weight": 1,
        "text": "(주 1)1,000 만원 투자시 투자자가 부담하는 투자기간별 총비용 예시’는 투자자가 1,000 만원을 투자했을 경우 직ㆍ간접적으로 부담할 것으로 예상되는 수수료 또는 총보수ㆍ비용을 누계적으로 산출한 것입니다."
    },
    {
        "id": "1",
        "index": 6,
        "bold": 0,
        "weight": 1,
        "text": "이익금은 모두 재투자하며, 연간 투자수익률은 5%, 수수료율 및 총 보수ㆍ비용비율은 일정하다고 가정하였습니다."
    },
    {
        "id": "1",
        "index": 7,
        "bold": 0,
        "weight": 1,
        "text": "그러나 실제 투자자가 부담하게 되는 보수 및 비용은 기타비용의 변동, 보수의 인상 또는 인하 여부 등에 따라 달라질 수 있음에 유의하시기 바랍니다."
    },
    {
        "id": "1",
        "index": 8,
        "bold": 0,
        "weight": 1,
        "text": "(주 2) 종류형 집합투자기구의 구체적인 투자비용은 투자설명서 제 2 부 13. 보수 및 수수료에 관한 사항(27 페이지)을 참고하시기 바랍니다."
    },
    {
        "id": "1",
        "index": 9,
        "bold": 0,
        "weight": 1,
        "text": "(주 3) 해당 집합투자기구는 오프라인 클래스에 비해 일반적으로 투자비용이 저렴한 온라인 클래스가 설정되 지 않았습니다."
    },
    {
        "id": "1",
        "index": 10,
        "bold": 0,
        "weight": 1,
        "text": "(주 4) ‘동종유형 총보수’는 한국금융투자협회에서 공시하는 동종유형 집합투자기구 전체의 평균 총보수비용을 의미합니다. (2024 년 2 월말 기준)"
    },
    {
        "id": "4",
        "index": 0,
        "bold": 0,
        "weight": 0,
        "text": "(주 1) 비교지수 : (0.9 * [MSCI_EM_BRIC_USD]) + (0.1 * [CALL 금리]) (비교지수 성과에는 투자신탁에 부과되는 보수 및 비용이 반영되지 않음) (주 2) 연평균 수익률은 해당 기간동안의 누적수익률을 기하평균방식으로 계산한 것으로 집합투자기구 총비용 지급후 해당기간동안의 세전평균 수익률을 나타내는 수치입니다."
    },
    {
        "id": "4",
        "index": 1,
        "bold": 0,
        "weight": 0,
        "text": "(주 3) 수익률 변동성(표준편차)은 해당기간 펀드의 연환산 주간수익률이 평균수익률에서 통상적으로 얼마만큼 등락했는지를 보여주는 수치로서, 변동성이 높을수록 수익률 등락이 빈번해 펀드의 손실위험이 높다는 것을 의미합니다."
    },
    {
        "id": "4",
        "index": 2,
        "bold": 0,
        "weight": 0,
        "text": "(주 4) 해당 집합투자기구의 투자실적의 자세한 사항은 정식 투자설명서를 참고하시기 바랍니다."
    },
    {
        "id": "4",
        "index": 3,
        "bold": 0,
        "weight": 0,
        "text": "(주 5) 상기 연평균 수익률은 투자설명서의 작성기준일로 산정한 수익률로, 실제 투자시점의 수익률은 크게 다를 수 있으므로 별도 확인이 필요합니다."
    },
    {
        "id": "5",
        "index": 0,
        "bold": 0,
        "weight": 0,
        "text": "(주 1) 운용전문인력의 최근 과거 3 년 이내에 운용한 집합투자기구의 명칭, 집합투자재산의 규모와 수익률 등은 금융투자협회 홈페이지(www.kofia.or.kr)에서 확인할 수 있습니다."
    },
    {
        "id": "5",
        "index": 1,
        "bold": 0,
        "weight": 0,
        "text": "(주 2) 동종집합투자기구 연평균 수익률은 해당 집합투자업자가 분류한 동일 유형 집합투자기구의 평균운용성과이며, 해당 운용전문인력의 평균운용성과는 해당 회사 근무기간 중 운용한 성과를 의미합니다."
    },
    {
        "id": "5",
        "index": 2,
        "bold": 0,
        "weight": 0,
        "text": "(주 3)‘운용경력년수’는 해당 운용전문인력이 과거 집합투자기구를 운용한 기간을 모두 합산한 기간입니다."
    },
    {
        "id": "6",
        "index": 0,
        "bold": 1,
        "weight": 1,
        "text": "ㆍ금융위원회가 투자설명서의 기재사항이 진실 또는 정확하다는 것을 인정하거나 그 증권의 가치를 보증 또는 승인하지 아니함을 유의하시기 바랍니다."
    },
    {
        "id": "6",
        "index": 1,
        "bold": 1,
        "weight": 1,
        "text": "ㆍ간이투자설명서는 증권신고서 효력발생일까지 기재사항 중 일부가 변경될 수 있으며, 개방형 집합투자증권인 경우 효력발생일 이후에도 변경될 수 있습니다."
    },
    {
        "id": "7",
        "index": 0,
        "bold": 0,
        "weight": 1,
        "text": "ㆍ투자 판단 시 증권신고서와 투자설명서 또는 간이투자설명서를 참고할 수 있으며, 투자자는 간이투자설명서 대신 투자설명서의 교부를 요청할 수 있습니다."
    },
    {
        "id": "7",
        "index": 1,
        "bold": 0,
        "weight": 1,
        "text": "ㆍ이 집합투자증권의 투자위험등급을 확인하시고, 귀하의 투자 경력이나 투자성향에 적합한 상품인지 신중한 투자결정을 하시기 바랍니다."
    },
    {
        "id": "7",
        "index": 2,
        "bold": 1,
        "weight": 1,
        "text": "ㆍ원본손실 위험 등 집합투자기구와 관련된 투자위험에 대해서는 증권신고서 및 투자설명서 또는 간이투자설명서의 본문 내 투자위험 부분을 참고하시기 바랍니다."
    },
    {
        "id": "7",
        "index": 3,
        "bold": 1,
        "weight": 1,
        "text": "ㆍ증권신고서, 투자설명서상 기재된 투자전략에 따른 투자목적 또는 성과목표는 반드시 실현된다는 보장은 없습니다."
    },
    {
        "id": "7",
        "index": 4,
        "bold": 1,
        "weight": 1,
        "text": "또한 과거의 투자실적이 장래에도 실현된다는 보장은 없습니다."
    },
    {
        "id": "7",
        "index": 5,
        "bold": 1,
        "weight": 1,
        "text": "ㆍ집합투자기구가 설정 후 1 년이 경과하였음에도 설정액이 50 억원 미만(소규모펀드)인 경우 분산투자가 어려워 효율적인 자산운용이 곤란하거나 임의해지 될 수 있으니, 투자 시 소규모펀드 여부를 확인 하시기 바라며 소규모펀드 해당여부는 금융투자협회, 판매회사, 자산운용사 홈페이지에서 확인할 수 있습니다."
    },
    {
        "id": "7",
        "index": 6,
        "bold": 0,
        "weight": 1,
        "text": "※ 추가적인 투자자 유의사항은 투자설명서 ‘투자결정시 유의사항 안내’를 참조 이 투자신탁은 투자 실적에 따른 실적배당상품으로 관련법령은 이에 대해서는 원리금을 보장하거나 보호하지 않습니다."
    },
    {
        "id": "7",
        "index": 7,
        "bold": 0,
        "weight": 1,
        "text": "따라서 투자원본의 전부 또는 일부에 대한 손실의 위험이 존재하며 투자금액의 손실 내지 감소의 위험은 전적으로 투자자가 부담합니다."
    },
    {
        "id": "7",
        "index": 8,
        "bold": 0,
        "weight": 1,
        "text": "집합투자업자나 판매회사 등 어떤 당사자도 투자손실에 대하여 책임을 지지 아니합니다."
    },
    {
        "id": "7",
        "index": 9,
        "bold": 0,
        "weight": 1,
        "text": "투자대상인 집합투자증권은 개별 국내 및 해외 국가의 법률에 의해서 설립된 법인이 발행한 주식에 주로 투자하기 때문에 운용성과는 동 국가들의 주식의 가격변동에 의해 결정됩니다."
    },
    {
        "id": "7",
        "index": 10,
        "bold": 0,
        "weight": 1,
        "text": "이 투자신탁은 외화 표시자산에 투자할 수 있으므로 해당 표시 통화와 원화 간의 환율변동 위험에 노출될 수 있습니다."
    },
    {
        "id": "7",
        "index": 11,
        "bold": 0,
        "weight": 1,
        "text": "따라서 외국 통화의 환율변동으로 당해 투자신탁재산의 가치변동에 영향을 줄 수 있으므로 자산운용사는 환헤지를 수행합니다."
    },
    {
        "id": "7",
        "index": 12,
        "bold": 0,
        "weight": 1,
        "text": "주된 전략으로 달러화, 유로화, 엔화 및 파운드화 외화표시 자산에 대하여 목표 환헤지 비율은 투자금액의 90%이상이나, 시장상황 등에 따라 환해지 비율이 조정될 수 있습니다."
    },
    {
        "id": "7",
        "index": 13,
        "bold": 0,
        "weight": 1,
        "text": "다만, 헤지 전략을 수행함에 있어, 환헤지 거래상대방의 거래불능 상황 또는 해당 통화가 일시적 혹은 상당기간 시장에서 거래되지 못하는 상황 등 환헤지 전략수행이 불가능한 상황에 직면할 수 있으며, 이 경우 헤지 거래가 충분히 실행되지 못하여 환율변동 위험이 감소되지 않을 수 있습니다."
    },
    {
        "id": "7",
        "index": 14,
        "bold": 0,
        "weight": 1,
        "text": "주요 투자대상인 피투자집합투자기구의 집합투자증권은 개별적인 운용전략하에 운용되며 개별적인 포트폴리오를 보유하고 있습니다."
    },
    {
        "id": "7",
        "index": 15,
        "bold": 0,
        "weight": 1,
        "text": "또한 운용전략에 따라 그 세부내역의 전부 또는 일부가 공개되지 않을 수 있기 때문에 투자하는 집합투자증권에 대한 정보를 충분히 얻지 못할 수 있습니다."
    },
    {
        "id": "7",
        "index": 16,
        "bold": 0,
        "weight": 1,
        "text": "결과적으로 타 집합투자증권에 주로 투자하는 투자 신탁의 투자자는 직접 자산을 투자하는 투자신탁에 비해 상대적으로 더 높은 기회비용과 손실을 부담할 위험이 있습니다."
    },
    {
        "id": "7",
        "index": 17,
        "bold": 0,
        "weight": 1,
        "text": "이 투자신탁 재산의 가치는 투자신탁 재산이 보유하고 있는 해외 유가증권, 파생상품, 단기 금융상품을 발행한 개별회사가 신용등급의 하락 또는 부도 등과 같은 신용사건에 노출되는 경우 급격히 변동될 수 있습니다."
    },
    {
        "id": "7",
        "index": 18,
        "bold": 0,
        "weight": 1,
        "text": "이 투자신탁은 투자대상 국가의 지정학적 위험 및 투자유가증권의 가치에 부정적으로 작용하는 관련 증권시장의 법령 및 제도의 급격한 변화에 노출되어 있습니다."
    },
    {
        "id": "7",
        "index": 19,
        "bold": 0,
        "weight": 1,
        "text": "이 투자신탁은 투자하는 국가 등의 정치적, 법적, 경제적 또는 규제환경의 변화로 인해서 발생할 수 있는 국가 위험에 노출됩니다."
    },
    {
        "id": "7",
        "index": 20,
        "bold": 0,
        "weight": 1,
        "text": "투자신탁(존속하는 동안 투자금을 추가로 모집할 수 있는 투자신탁으로 한정한다)을 설정한 후 1 년이 되는 날에 원본액이 50 억원 미만인 경우 또는 투자신탁(존속하는 동안 투자금을 추가로 모집할 수 있는 투자신탁으로 한정한다)을 설정하고 1 년이 지난 후 1 개월간 계속하여 투자신탁의 원본액이 50 억원 미만인 경우 집합투자업자가 투자신탁을 해지하는 등의 사유로 투자자의 동의 없이 투자신탁이 해지될 수 있습니다."
    },
    {
        "id": "7",
        "index": 21,
        "bold": 0,
        "weight": 1,
        "text": "(주1) 이 투자신탁의 투자위험에 대한 보다 상세한 설명은 투자설명서 제2부 10. 집합투자기구의 투자위험을 참 고하시기 바랍니다."
    },
    {
        "id": "8",
        "index": 0,
        "bold": 0,
        "weight": 0,
        "text": "17 시 이전 - 4 영업일 기준가, 9 영업일 지급 17 시 경과후 - 5 영업일 기준가, 10 영업일 지급"
    },
    {
        "id": "9",
        "index": 0,
        "bold": 0,
        "weight": 0,
        "text": "산정방법: 당일에 공고되는 기준가격[당해 종류 수익증권의 기준가격]은 공고ㆍ게시일 전날의 대차대조표상에 계상된 투자신탁[당해 종류 수익증권의 상당액]의 자산총액에서 부채총액을 차감한 금액(순자산총액[당해 종류 수익증권의 순자산총액])을 공고ㆍ게시일 전날의 수익증권[당해 종류 수익증권] 총좌수로 나누어 산정하며, 1,000 좌 단위로 원미만 셋째자리에서 4 사 5 입하여 원미만 둘째자리까지 계산합니다."
    },
    {
        "id": "9",
        "index": 1,
        "bold": 0,
        "weight": 0,
        "text": "공시장소: 판매회사 영업점, 집합투자업자ㆍ판매회사ㆍ한국금융투자협회 홈페이지 ※ 집합투자기구에 대한 과세: 집합투자기구 단계에서는 별도의 소득과세 부담이 없는 것이 원칙입니다."
    },
    {
        "id": "9",
        "index": 2,
        "bold": 0,
        "weight": 0,
        "text": "※ 수익자에 대한 과세: 거주자 개인이 받는 투자신탁으로부터의 과세이익에 대해서는 15.4% (소득세 14%, 주민세 1.4%)의 세율로 원천징수 됩니다."
    },
    {
        "id": "9",
        "index": 3,
        "bold": 0,
        "weight": 0,
        "text": "이러한 소득은 개인의 연간 금융소득(이자, 배당소득)이 2 천만원 이하인 경우에는 분리과세 원천징수로 납세의무 종결되나, 연간 금융소득(이자, 배당소득)이 2 천만원을 초과하는 경우에는 유형별 소득을 합산하여 개인소득세율로 종합과세 됩니다."
    },
    {
        "id": "9",
        "index": 4,
        "bold": 0,
        "weight": 0,
        "text": "*자세한 내용은 투자설명서를 참고하시기 바랍니다."
    },
    {
        "id": "9",
        "index": 5,
        "bold": 0,
        "weight": 0,
        "text": "집합투자업자는 수익자의 전환청구 여부와 관계없이 수익자가 보유하고 있는 종류 C1 수익증권 및 종류 C2 수익증권의 잔고에 대하여 다음 각 호에서 정하는 바에 따라 수익증권을 전환합니다."
    },
    {
        "id": "9",
        "index": 6,
        "bold": 0,
        "weight": 0,
        "text": "다만, 수익자가 최초로 매입하는 수익증권은 종류 C1 수익증권에 한합니다."
    },
    {
        "id": "9",
        "index": 7,
        "bold": 0,
        "weight": 0,
        "text": "1. 수수료미징구-오프라인-보수체감형(C1) : 제한없음"
    },
    {
        "id": "9",
        "index": 8,
        "bold": 0,
        "weight": 0,
        "text": "2. 수수료미징구-오프라인-보수체감형(C2) : 종류 C1 수익증권의 최초 매수일로부터 1 년이 되는 날에 종류 C2 수익증권으로 전환 3. 수수료미징구-오프라인-보수체감형(C3) : 종류 C1 수익증권의 최초 매수일로부터 2 년이 되는 날에 종류 C3 수익증권으로 전환 ※ 기타 전환 관련 세부 사항은 투자설명서를 참조하시기 바랍니다."
    },
    {
        "id": "15",
        "index": 0,
        "bold": 0,
        "weight": 0,
        "text": "집합투자업자의 사업목적, 요약 재무정보에 관한 사항은 투자설명서 제 4 부 1. 집합투자업자에 관한 사항(38 페이지)을 참고하시기 바랍니다."
    },
    {
        "id": "17",
        "index": 0,
        "bold": 0,
        "weight": 0,
        "text": "정해진 신탁계약 기간은 없음"
    },
    {
        "id": "19",
        "index": 0,
        "bold": 0,
        "weight": 0,
        "text": "이 집합투자기구는 종류형 집합투자기구입니다."
    },
    {
        "id": "19",
        "index": 1,
        "bold": 0,
        "weight": 0,
        "text": "집합투자기구의 종류는 판매수수료 부과방식- 판매경로-기타 펀드특성에 따라 3 단계로 구분되며, 집합투자기구 종류의 대표적인 차이는 다음과 같습니다."
    },
    {
        "id": "19",
        "index": 2,
        "bold": 0,
        "weight": 0,
        "text": "수수료 미징구(C) 집합투자증권 매입 또는 환매시점에 일시 징구되는 판매수수료는 없는 집합투자기구입 니다."
    },
    {
        "id": "19",
        "index": 3,
        "bold": 1,
        "weight": 0,
        "text": "판매회사의 온라인전용으로 판매되는 집합투자기구로 오프라인으로 판매되는 집합투자 기구보다 판매수수료 및 판매보수가 저렴한 집합투자기구입니다."
    },
    {
        "id": "19",
        "index": 4,
        "bold": 1,
        "weight": 0,
        "text": "다만, 판매회사로부터 별도의 투자권유 및 상담서비스는 제공되지 않습니다."
    },
    {
        "id": "19",
        "index": 5,
        "bold": 1,
        "weight": 0,
        "text": "오프라인전용(판매회사 창구)으로 판매되는 집합투자기구로 온라인으로 판매되는 집합투 자기구보다 판매수수료 및 판매보수가 높은 집합투자기구입니다."
    },
    {
        "id": "19",
        "index": 6,
        "bold": 1,
        "weight": 0,
        "text": "다만, 판매회사로부터 별도의 투자권유 및 상담서비스가 제공됩니다."
    },
    {
        "id": "19",
        "index": 7,
        "bold": 0,
        "weight": 0,
        "text": "판매수수료미징구형(C) 집합투자기구이며 이연판매보수(CDSC) 프로그램에 따라 판매보수 를 적용하기 때문에 별도의 전환 청구 없이 집합투자증권의 보유기간이 경과함에 따라 판매보수가 낮은 종류의 집합투자기구로 자동 전환됩니다."
    }
]